cubicweb_jsonb/__init__.py
cubicweb_jsonb/__pkginfo__.py
cubicweb_jsonb/schema.py
cubicweb_jsonb/site_cubicweb.py
cubicweb_jsonb/i18n/en.po
cubicweb_jsonb/i18n/fr.po
cubicweb_jsonb/migration/postcreate.py
cubicweb_jsonb-0.4.0.dist-info/METADATA
cubicweb_jsonb-0.4.0.dist-info/WHEEL
cubicweb_jsonb-0.4.0.dist-info/entry_points.txt
cubicweb_jsonb-0.4.0.dist-info/top_level.txt
cubicweb_jsonb-0.4.0.dist-info/RECORD
