Metadata-Version: 2.1
Name: cubicweb-jsonb
Version: 0.4.0
Summary: Add jsonb type to CubicWeb
Home-page: https://forge.extranet.logilab.fr/cubicweb/cubes/cubicweb-jsonb
Author: LOGILAB S.A. (Paris, FRANCE)
Author-email: contact@logilab.fr
License: LGPL
Platform: UNKNOWN
Classifier: Environment :: Web Environment
Classifier: Framework :: CubicWeb
Classifier: Programming Language :: Python
Classifier: Programming Language :: JavaScript
Requires-Dist: cubicweb (<3.38.0,>=3.24.0)
Requires-Dist: psycopg2-binary (>=2.7.2)
Requires-Dist: six (>=1.4.0)
